smallfileserver/__init__.py
smallfileserver/__main__.py
smallfileserver/fileserver.py
smallfileserver/versions.py
smallfileserver-0.4.0.dist-info/LICENSE
smallfileserver-0.4.0.dist-info/METADATA
smallfileserver-0.4.0.dist-info/WHEEL
smallfileserver-0.4.0.dist-info/top_level.txt
smallfileserver-0.4.0.dist-info/RECORD
