Metadata-Version: 2.1
Name: smallfileserver
Version: 0.4.0
Summary: A webpage that supports file upload and download
Author-email: OSmile <whghcyx@outlook.com>
Project-URL: Homepage, https://github.com/WHG555/smallfileserver
Project-URL: Bug Tracker, https://github.com/WHG555/smallfileserver/issues
Classifier: Programming Language :: Python :: 3
Classifier: License :: OSI Approved :: MIT License
Classifier: Operating System :: OS Independent
Requires-Python: >=3.5
License-File: LICENSE
